[{"date":"2015-02-28","value":2025},{"date":"2015-03-03","value":5375},{"date":"2015-03-05","value":3875},{"date":"2015-03-07","value":2160},{"date":"2015-03-10","value":4300},{"date":"2015-03-12","value":4000},{"date":"2015-03-14","value":7395},{"date":"2015-03-17","value":4175},{"date":"2015-03-19","value":4350},{"date":"2015-03-21","value":8920},{"date":"2015-03-24","value":8200},{"date":"2015-03-28","value":8265},{"date":"2015-03-31","value":7665},{"date":"2015-04-02","value":3875},{"date":"2015-04-04","value":9120},{"date":"2015-04-07","value":5375},{"date":"2015-04-09","value":3875},{"date":"2015-04-11","value":10565},{"date":"2015-04-14","value":5500},{"date":"2015-04-16","value":3200},{"date":"2015-04-18","value":6250},{"date":"2015-04-21","value":5425},{"date":"2015-04-23","value":6360},{"date":"2015-04-28","value":6125},{"date":"2015-05-02","value":11375},{"date":"2015-05-05","value":8295},{"date":"2015-05-07","value":2475},{"date":"2015-05-09","value":6625},{"date":"2015-05-12","value":5875},{"date":"2015-05-14","value":5600},{"date":"2015-05-16","value":11450},{"date":"2015-05-19","value":5875},{"date":"2015-05-23","value":8035},{"date":"2015-05-26","value":4815},{"date":"2015-05-30","value":11400},{"date":"2015-06-02","value":6360},{"date":"2015-06-05","value":1395},{"date":"2015-06-06","value":11010},{"date":"2015-06-09","value":6315},{"date":"2015-06-11","value":3625},{"date":"2015-06-13","value":6625},{"date":"2015-06-16","value":6125},{"date":"2015-06-18","value":3875},{"date":"2015-06-20","value":10590},{"date":"2015-06-23","value":3750},{"date":"2015-06-25","value":4000},{"date":"2015-06-27","value":10695}]